lang/Lang.py
lang/__init__.py
lang/config/lang.py
lang/facades/Lang.py
lang/facades/Lang.pyi
lang/facades/__init__.py
lang/providers/LangProvider.py
lang/providers/__init__.py
masonite_lang-1.1.1.dist-info/LICENSE
masonite_lang-1.1.1.dist-info/METADATA
masonite_lang-1.1.1.dist-info/WHEEL
masonite_lang-1.1.1.dist-info/top_level.txt
masonite_lang-1.1.1.dist-info/RECORD
